sqlbag/__init__.py
sqlbag/createdrop.py
sqlbag/misc.py
sqlbag/sqla.py
sqlbag/sqla_orm.py
sqlbag/util_mysql.py
sqlbag/util_pg.py
sqlbag/flask/__init__.py
sqlbag/flask/sessions.py
sqlbag/pg/__init__.py
sqlbag/pg/datetimes.py
sqlbag/pg/postgresql.py
sqlbag-0.1.1617247075.dist-info/LICENSE
sqlbag-0.1.1617247075.dist-info/METADATA
sqlbag-0.1.1617247075.dist-info/WHEEL
sqlbag-0.1.1617247075.dist-info/top_level.txt
sqlbag-0.1.1617247075.dist-info/RECORD
