Metadata-Version: 2.1
Name: sqlbag
Version: 0.1.1617247075
Summary: various snippets of SQL-related boilerplate
Home-page: https://github.com/djrobstep/sqlbag
Author: Robert Lechte
Author-email: robertlechte@gmail.com
License: UNKNOWN
Platform: UNKNOWN
Classifier: Development Status :: 3 - Alpha
Provides-Extra: pg
Provides-Extra: pendulum
Provides-Extra: maria
